cs103/__init__.py
cs103/custom/__init__.py
cs103/custom/custom.js
cs103/custom/custom.py
cs103/custom/ipython_config.py
cs103/image/__init__.py
cs103/image/image.py
cs103/image/imagetest.py
cs103/iofunc/__init__.py
cs103/iofunc/example.py
cs103/iofunc/iofunc.py
cs103/parsing/__init__.py
cs103/parsing/parsing.py
cs103/pokemon/__init__.py
cs103/pokemon/pokemon.csv
cs103/pokemon/pokemon.py
cs103/pokemon/pokemon_test.py
cs103/submit/__init__.py
cs103/submit/submit.py
cs103/testing/__init__.py
cs103/testing/example.py
cs103/testing/testing.py
cs103/typecheck/__init__.py
cs103/typecheck/example.py
cs103/typecheck/typecheck.py
cs103-0.3.10.dist-info/METADATA
cs103-0.3.10.dist-info/WHEEL
cs103-0.3.10.dist-info/top_level.txt
cs103-0.3.10.dist-info/RECORD
